dps.py
setup.py
django_packages_search.egg-info/PKG-INFO
django_packages_search.egg-info/SOURCES.txt
django_packages_search.egg-info/dependency_links.txt
django_packages_search.egg-info/requires.txt
django_packages_search.egg-info/top_level.txt