Metadata-Version: 1.1
Name: django-packages-search
Version: 0.11
Summary: A command line tool for searching within djangopackages.com
Home-page: https://github.com/vahidR/django-packages-search
Author: Vahid Rafiei
Author-email: vahid.rafiei@gmail.com
License: UNKNOWN
Keywords: django,django packages,python
Platform: UNKNOWN
Classifier: Environment :: Console
Classifier: Intended Audience :: Developers
Classifier: License :: OSI Approved :: GNU General Public License v2 (GPLv2)
Classifier: Operating System :: OS Independent
Classifier: Programming Language :: Python
Classifier: Topic :: Software Development :: Libraries :: Python Modules
